{"x_individuos": 148, "suma_notas": 789.2399999999996, "lugares": {"CHINCHEROS": {"x_individuos": 56, "nota": 300.8400000000001}, "SAN MIGUEL": {"x_individuos": 28, "nota": 122.08}, "TAMBO": {"x_individuos": 64, "nota": 366.31999999999994}}, "escuelas": {"AGRONOMIA": {"CHINCHEROS": {"x_individuos": 1, "nota": 6.4}, "SAN MIGUEL": {"x_individuos": 1, "nota": 4.56}, "TAMBO": {"x_individuos": 3, "nota": 12.959999999999999}}, "BIOLOGIA": {"CHINCHEROS": {"x_individuos": 2, "nota": 21.16}, "SAN MIGUEL": {"x_individuos": 1, "nota": 8.12}, "TAMBO": {"x_individuos": 7, "nota": 44.68000000000001}}, "EDUCACION INICIAL": {"CHINCHEROS": {"x_individuos": 2, "nota": 7.4799999999999995}, "TAMBO": {"x_individuos": 3, "nota": 19.439999999999998}}, "EDUCACION PRIMARIA": {"CHINCHEROS": {"x_individuos": 2, "nota": 13.16}}, "EDUCACION SECUNDARIA": {"CHINCHEROS": {"x_individuos": 1, "nota": 5.48}, "TAMBO": {"x_individuos": 2, "nota": 8.120000000000001}}, "EDUCACION FISICA": {"CHINCHEROS": {"x_individuos": 1, "nota": 3.28}, "SAN MIGUEL": {"x_individuos": 3, "nota": 16.04}, "TAMBO": {"x_individuos": 1, "nota": 3.72}}, "ADMINISTRACION DE EMPRESAS": {"CHINCHEROS": {"x_individuos": 1, "nota": 6.04}, "SAN MIGUEL": {"x_individuos": 2, "nota": 8.96}, "TAMBO": {"x_individuos": 6, "nota": 27.64}}, "CONTABILIDAD Y AUDITORIA": {"CHINCHEROS": {"x_individuos": 1, "nota": 2.4}, "SAN MIGUEL": {"x_individuos": 3, "nota": 16.880000000000003}, "TAMBO": {"x_individuos": 1, "nota": 6.12}}, "ECONOMIA": {"CHINCHEROS": {"x_individuos": 2, "nota": 9.64}, "SAN MIGUEL": {"x_individuos": 1, "nota": 3.6}, "TAMBO": {"x_individuos": 1, "nota": 6.08}}, "TRABAJO SOCIAL": {"SAN MIGUEL": {"x_individuos": 2, "nota": 9.36}}, "DERECHO": {"CHINCHEROS": {"x_individuos": 8, "nota": 41.04}, "SAN MIGUEL": {"x_individuos": 2, "nota": 8.600000000000001}, "TAMBO": {"x_individuos": 5, "nota": 37.4}}, "ENFERMERIA": {"CHINCHEROS": {"x_individuos": 6, "nota": 18.599999999999998}, "SAN MIGUEL": {"x_individuos": 2, "nota": 7.88}, "TAMBO": {"x_individuos": 8, "nota": 40.84}}, "INGENIERIA DE MINAS": {"CHINCHEROS": {"x_individuos": 3, "nota": 16.72}, "SAN MIGUEL": {"x_individuos": 1, "nota": 2.4}}, "INGENIERIA CIVIL": {"CHINCHEROS": {"x_individuos": 8, "nota": 58.32}, "SAN MIGUEL": {"x_individuos": 4, "nota": 11.88}, "TAMBO": {"x_individuos": 8, "nota": 49.04}}, "INGENIERIA QUIMICA": {"CHINCHEROS": {"x_individuos": 1, "nota": 5.92}, "TAMBO": {"x_individuos": 1, "nota": 4.72}}, "OBSTETRICIA": {"CHINCHEROS": {"x_individuos": 3, "nota": 11.96}, "SAN MIGUEL": {"x_individuos": 3, "nota": 8.64}, "TAMBO": {"x_individuos": 7, "nota": 37.48}}, "FARMACIA Y BIOQUIMICA": {"CHINCHEROS": {"x_individuos": 5, "nota": 21.400000000000002}, "SAN MIGUEL": {"x_individuos": 1, "nota": 5.52}, "TAMBO": {"x_individuos": 4, "nota": 17.0}}, "INGENIERIA AGRICOLA": {"TAMBO": {"x_individuos": 1, "nota": 9.0}}, "CIENCIAS DE LA COMUNICACION": {"TAMBO": {"x_individuos": 1, "nota": 9.08}}, "MEDICINA VETERINARIA": {"CHINCHEROS": {"x_individuos": 2, "nota": 8.68}, "SAN MIGUEL": {"x_individuos": 1, "nota": 3.72}, "TAMBO": {"x_individuos": 1, "nota": 4.96}}, "INGENIERIA DE SISTEMAS": {"CHINCHEROS": {"x_individuos": 7, "nota": 43.160000000000004}, "SAN MIGUEL": {"x_individuos": 1, "nota": 5.92}, "TAMBO": {"x_individuos": 4, "nota": 28.04}}}}